rebnf/__init__.py
rebnf/__main__.py
rebnf/lexers.py
rebnf/parsers.py
rebnf/parsetab.py
rebnf/grammar/modular.rebnf
rebnf/grammar/spec.rebnf
rebnf-0.9.dist-info/entry_points.txt
rebnf-0.9.dist-info/LICENSE.md
rebnf-0.9.dist-info/WHEEL
rebnf-0.9.dist-info/METADATA
rebnf-0.9.dist-info/RECORD
