Metadata-Version: 2.1
Name: rebnf
Version: 0.9
Summary: ReBNF: Regexes for Extended Backus-Naur Form (EBNF)
Keywords: bnf,ebnf,rebnf,regex,regexes,backus-naur form,extended backus-naur form,syntax,metasyntax,lexer,parser,context-free grammar,formal language,grammar,language,text processing
Author-email: opsocket <opsocket@pm.me>
Classifier: Development Status :: 4 - Beta
Classifier: Intended Audience :: Developers
Classifier: License :: OSI Approved :: GNU General Public License v3 or later (GPLv3+)
Classifier: Operating System :: OS Independent
Classifier: Programming Language :: Python :: 3
Classifier: Topic :: Software Development :: Libraries
Classifier: Topic :: Software Development
Classifier: Topic :: Text Processing
Requires-Dist: ply
Requires-Dist: black ; extra == "dev"
Requires-Dist: flake8 ; extra == "dev"
Requires-Dist: flit ; extra == "dev"
Requires-Dist: build ; extra == "dev"
Requires-Dist: twine ; extra == "dev"
Project-URL: Repository, https://gitlab.com/opsocket/rebnf.git
Provides-Extra: dev
Provides-Extra: docs
